cpskin.localfood-1.0.3-py2.7-nspkg.pth
cpskin/localfood/__init__.py
cpskin/localfood/configure.zcml
cpskin/localfood/interfaces.py
cpskin/localfood/setuphandlers.py
cpskin/localfood/testing.py
cpskin/localfood/utils.py
cpskin/localfood/behavior/__init__.py
cpskin/localfood/behavior/configure.zcml
cpskin/localfood/behavior/contact.py
cpskin/localfood/behavior/indexer.py
cpskin/localfood/behavior/label.py
cpskin/localfood/browser/__init__.py
cpskin/localfood/browser/configure.zcml
cpskin/localfood/browser/mapview.py
cpskin/localfood/browser/matchmaking.py
cpskin/localfood/browser/overrides/.gitkeep
cpskin/localfood/browser/static/.gitkeep
cpskin/localfood/browser/templates/local_product_form.pt
cpskin/localfood/browser/templates/local_product_subscription.pt
cpskin/localfood/browser/templates/mapview.pt
cpskin/localfood/browser/templates/producer_discovery.pt
cpskin/localfood/content/__init__.py
cpskin/localfood/content/community_garden.pt
cpskin/localfood/content/community_garden.py
cpskin/localfood/content/configure.zcml
cpskin/localfood/content/hompepage.pt
cpskin/localfood/content/project.pt
cpskin/localfood/content/project.py
cpskin/localfood/faceted/__init__.py
cpskin/localfood/faceted/cards.pt
cpskin/localfood/faceted/configure.zcml
cpskin/localfood/locales/cpskin.localfood.pot
cpskin/localfood/locales/eea.pot
cpskin/localfood/locales/plone.pot
cpskin/localfood/locales/update.sh
cpskin/localfood/locales/fr/LC_MESSAGES/cpskin.localfood.po
cpskin/localfood/locales/fr/LC_MESSAGES/eea.po
cpskin/localfood/locales/fr/LC_MESSAGES/plone.po
cpskin/localfood/profiles/default/browserlayer.xml
cpskin/localfood/profiles/default/catalog.xml
cpskin/localfood/profiles/default/import_steps.xml
cpskin/localfood/profiles/default/metadata.xml
cpskin/localfood/profiles/default/registry.xml
cpskin/localfood/profiles/default/types.xml
cpskin/localfood/profiles/default/workflows.xml
cpskin.localfood-1.0.3.dist-info/DESCRIPTION.rst
cpskin.localfood-1.0.3.dist-info/METADATA
cpskin.localfood-1.0.3.dist-info/RECORD
cpskin.localfood-1.0.3.dist-info/WHEEL
cpskin.localfood-1.0.3.dist-info/entry_points.txt
cpskin.localfood-1.0.3.dist-info/metadata.json
cpskin.localfood-1.0.3.dist-info/namespace_packages.txt
cpskin.localfood-1.0.3.dist-info/top_level.txt
