Metadata-Version: 2.0
Name: cpskin.localfood
Version: 1.0.3
Summary: Local food implementation for IA Web
Home-page: https://pypi.python.org/pypi/cpskin.localfood
Author: Martin Peeters
Author-email: martin.peeters@affinitic.be
License: GPL version 2
Keywords: Python Plone
Platform: UNKNOWN
Classifier: Environment :: Web Environment
Classifier: Framework :: Plone
Classifier: Framework :: Plone :: 4.3
Classifier: Programming Language :: Python
Classifier: Programming Language :: Python :: 2.7
Classifier: Operating System :: OS Independent
Classifier: License :: OSI Approved :: GNU General Public License v2 (GPLv2)
Provides-Extra: test
Requires-Dist: plone.api
Requires-Dist: Products.GenericSetup (>=1.8.2)
Requires-Dist: setuptools
Requires-Dist: z3c.jbot
Requires-Dist: plone.app.dexterity
Requires-Dist: plone.app.referenceablebehavior
Requires-Dist: plone.app.relationfield
Requires-Dist: plone.app.lockingbehavior
Requires-Dist: cpskin.core
Requires-Dist: collective.behavior.richdescription
Provides-Extra: test
Requires-Dist: plone.app.testing; extra == 'test'
Requires-Dist: plone.testing; extra == 'test'
Requires-Dist: plone.app.robotframework[debug]; extra == 'test'
